audio_sdk/__init__.py
audio_sdk/save_to_word_srt.py
audio_sdk/transcriber.py
audio_sdk/video_utils.py
tests/__init__.py
tests/test_transcriber.py
audio_sdk-0.1.0.dist-info/METADATA
audio_sdk-0.1.0.dist-info/WHEEL
audio_sdk-0.1.0.dist-info/top_level.txt
audio_sdk-0.1.0.dist-info/RECORD
