Metadata-Version: 2.1
Name: audio-sdk
Version: 0.1.0
Summary: A Python SDK for audio transcription
Home-page: https://github.com/your_username/audio_sdk
Author: zhangying
Author-email: imuzhangying@163.com
Classifier: Programming Language :: Python :: 3
Classifier: License :: OSI Approved :: MIT License
Classifier: Operating System :: OS Independent
Requires-Python: >=3.6
Requires-Dist: dashscope
Requires-Dist: requests
Requires-Dist: python-docx
